grappy.py
GrappyLfjv-0.0.21.dist-info/LICENSE
GrappyLfjv-0.0.21.dist-info/METADATA
GrappyLfjv-0.0.21.dist-info/WHEEL
GrappyLfjv-0.0.21.dist-info/top_level.txt
GrappyLfjv-0.0.21.dist-info/RECORD
