Metadata-Version: 2.1
Name: GrappyLfjv
Version: 0.0.21
Summary: Simplification de la création de graphiques avec matplotlib
Home-page: https://github.com/Benjamin-Trevian/Grappy
Author: Benjamin Trévian
Author-email: benjamin.trevian@hotmail.com
License-File: LICENSE
Requires-Dist: matplotlib (>3.0)
